README.md
setup.py
chaosloader/__init__.py
chaosloader.egg-info/PKG-INFO
chaosloader.egg-info/SOURCES.txt
chaosloader.egg-info/dependency_links.txt
chaosloader.egg-info/entry_points.txt
chaosloader.egg-info/requires.txt
chaosloader.egg-info/top_level.txt
chaosloader/src/__init__.py
chaosloader/src/cli.py
chaosloader/src/commands/__init__.py
chaosloader/src/commands/validate/__init__.py
chaosloader/src/commands/validate/command.py
chaosloader/src/commands/validate/environment/__init__.py
chaosloader/src/commands/validate/environment/config.py
chaosloader/src/commands/validate/environment/environment.py
chaosloader/src/utils/__init__.py
chaosloader/src/utils/decorators/__init__.py
chaosloader/src/utils/decorators/common.py
chaosloader/test/__init__.py
chaosloader/test/pytest.py
chaosloader/test/acceptance/__init__.py
chaosloader/test/unittest/__init__.py
chaosloader/test/unittest/conftest.py
chaosloader/test/unittest/validate/__init__.py
chaosloader/test/unittest/validate/environment/__init__.py
chaosloader/test/unittest/validate/environment/test_environment.py