Metadata-Version: 2.1
Name: chaosloader
Version: 0.0.0
Summary: Chaos loader command line
Home-page: https://github.com/albertoig/chaos-loader
Author: Alberto Iglesias Gallego
License: UNKNOWN
Platform: UNKNOWN
Requires-Python: >3.5.2
Provides-Extra: dev
